LICENSE.txt
MANIFEST.in
README
VERSION
contributors.txt
requirements.txt
setup.cfg
setup.py
nekbot/__init__.py
nekbot.plugins.geo.egg-info/PKG-INFO
nekbot.plugins.geo.egg-info/SOURCES.txt
nekbot.plugins.geo.egg-info/dependency_links.txt
nekbot.plugins.geo.egg-info/namespace_packages.txt
nekbot.plugins.geo.egg-info/not-zip-safe
nekbot.plugins.geo.egg-info/requires.txt
nekbot.plugins.geo.egg-info/top_level.txt
nekbot/plugins/__init__.py
nekbot/plugins/geo/__init__.py